mapof/core/__init__.py
mapof/core/glossary.py
mapof/core/matchings.py
mapof/core/printing.py
mapof/core/utils.py
mapof/core/distances/__init__.py
mapof/core/distances/inner_distances.py
mapof/core/embedding/__init__.py
mapof/core/embedding/embed.py
mapof/core/embedding/initial_positions.py
mapof/core/embedding/kamada_kawai/__init__.py
mapof/core/embedding/kamada_kawai/energy_functions.py
mapof/core/embedding/kamada_kawai/kamada_kawai.py
mapof/core/embedding/kamada_kawai/optimization_algorithms.py
mapof/core/embedding/simulated_annealing/__init__.py
mapof/core/embedding/simulated_annealing/simulated_annealing.py
mapof/core/embedding/simulated_annealing/simulated_annealing_energy.py
mapof/core/features/__init__.py
mapof/core/features/common.py
mapof/core/features/distortion.py
mapof/core/features/mallows.py
mapof/core/features/monotonicity.py
mapof/core/features/register.py
mapof/core/features/stability.py
mapof/core/objects/Experiment.py
mapof/core/objects/Family.py
mapof/core/objects/Instance.py
mapof/core/objects/__init__.py
mapof/core/persistence/__init__.py
mapof/core/persistence/experiment_exports.py
mapof/core/persistence/experiment_imports.py
mapof-0.1.5.dist-info/licenses/LICENSE.txt
mapof-0.1.5.dist-info/METADATA
mapof-0.1.5.dist-info/WHEEL
mapof-0.1.5.dist-info/top_level.txt
mapof-0.1.5.dist-info/RECORD
