Metadata-Version: 2.4
Name: mapof
Version: 0.1.5
Summary: Map of Objects---essential parts
Author-email: Stanislaw Szufa <s.szufa@gmail.com>, Niclas Boehmer <niclas.boehmer@tu-berlin.de>, Andrzej Kaczmarczyk <andrzej.kaczmarczyk@agh.edu.pl>, Kasper Sapala <kasper.sapala@gmail.com>, Tomasz Was <tomasz.t.was@gmail.com>
License: Copyright (c) 2018-2024 Stanisław Szufa, Andrzej Kaczmarczyk, and others.
Classifier: Programming Language :: Python :: 3
Classifier: License :: OSI Approved :: MIT License
Classifier: Operating System :: OS Independent
Requires-Python: >=3.10
License-File: LICENSE.txt
Requires-Dist: numpy>=2.0.0
Requires-Dist: matplotlib~=3.9.4
Requires-Dist: pillow~=11.0.0
Requires-Dist: scipy~=1.14.1
Requires-Dist: networkx~=3.5.0
Requires-Dist: scikit-learn~=1.5.2
Requires-Dist: tikzplotlib~=0.10.1
Requires-Dist: gurobipy~=13.0.0
Requires-Dist: tqdm~=4.66.5
Dynamic: license-file
